beeflow_ajax/__init__.py
beeflow_ajax/lib/__init__.py
beeflow_ajax/lib/ajax_request.py
beeflow_ajax/lib/ajax_response.py
beeflow_ajax/lib/websocket_response.py
beeflow_ajax/lib/html_models/__init__.py
beeflow_ajax/lib/html_models/ajax_paginator_url.py
beeflow_ajax/lib/html_models/base_html_model.py
beeflow_ajax/lib/html_models/icon.py
beeflow_ajax/lib/html_models/img.py
beeflow_ajax/lib/html_models/label.py
beeflow_ajax/lib/html_models/pagination_button.py
beeflow_ajax/lib/html_models/table_header_element.py
beeflow_ajax/lib/html_models/td.py
beeflow_ajax/lib/html_models/url.py
beeflow_ajax/tests/__init__.py
beeflow_ajax/tests/test_ajax_response.py
beeflow_ajax-1.0.18.dist-info/LICENCE.md
beeflow_ajax-1.0.18.dist-info/LICENSE
beeflow_ajax-1.0.18.dist-info/METADATA
beeflow_ajax-1.0.18.dist-info/WHEEL
beeflow_ajax-1.0.18.dist-info/top_level.txt
beeflow_ajax-1.0.18.dist-info/RECORD
