Metadata-Version: 2.1
Name: beeflow-ajax
Version: 1.0.18
Summary: Library to maintain ajax and websockets communication without writing complicated code in JS
Home-page: https://github.com/beeflow/BeeflowAjaxPy
Author: Rafal Przetakowski
Author-email: office@beeflow.co.uk
Classifier: Programming Language :: Python :: 3
Classifier: License :: OSI Approved :: MIT License
Classifier: Operating System :: OS Independent
Requires-Python: >=3.11
License-File: LICENCE.md
License-File: LICENSE
